wrapper/__init__.py
wrapper/fastapiwrapper.py
analysisapi-0.0.3.dist-info/METADATA
analysisapi-0.0.3.dist-info/WHEEL
analysisapi-0.0.3.dist-info/top_level.txt
analysisapi-0.0.3.dist-info/RECORD
